LICENSE
MANIFEST.in
README.md
setup.py
mako_sugar/__init__.py
mako_sugar/mako_sugar.py
mako_sugar.egg-info/PKG-INFO
mako_sugar.egg-info/SOURCES.txt
mako_sugar.egg-info/dependency_links.txt
mako_sugar.egg-info/not-zip-safe
mako_sugar.egg-info/top_level.txt
test/__init__.py
test/test_process.py
test/test_sugar.py
test/util.py