Metadata-Version: 1.1
Name: mako-sugar
Version: 0.1.0
Summary: Syntax sugar for Python Mako templates
Home-page: https://github.com/marcpare/mako-sugar
Author: Marc Paré
Author-email: marc@smallredtile.com
License: MIT
Download-URL: https://github.com/marcpare/mako-sugar/tarball/0.1.0
Platform: UNKNOWN
